strawberry_django_optimizer/__init__.py
strawberry_django_optimizer/field.py
strawberry_django_optimizer/hints.py
strawberry_django_optimizer/query.py
strawberry_django_optimizer/resolver.py
strawberry_django_optimizer/store.py
strawberry_django_optimizer/utils.py
strawberry_django_optimizer-0.1.0.dist-info/LICENSE
strawberry_django_optimizer-0.1.0.dist-info/METADATA
strawberry_django_optimizer-0.1.0.dist-info/WHEEL
strawberry_django_optimizer-0.1.0.dist-info/top_level.txt
strawberry_django_optimizer-0.1.0.dist-info/RECORD
