Metadata-Version: 2.1
Name: strawberry-django-optimizer
Version: 0.1.0
Summary: Automatic query optimization for django and strawberry-graphql
Home-page: https://github.com/energy-efficiency/strawberry-django-optimizer
Author: OPTENDA GmbH
Author-email: openda@steag.com
License: UNKNOWN
Project-URL: Bug Tracker, https://github.com/energy-efficiency/strawberry-django-optimizer/issues
Platform: UNKNOWN
Classifier: Programming Language :: Python :: 3
Classifier: License :: OSI Approved :: MIT License
Classifier: Operating System :: OS Independent
Requires-Python: >=3.6
License-File: LICENSE
